Workbook

Sheet Site Selection Scorecard
B1: Site Name | D1: TM
B2: Site Address (Put in full address w/City & State): | D2: TM
B3: Tenant Improvement Allowance/Landlord Work Total $ (Dollar values only) | D3: TM
B4: Description of LL Work | D4: TM
B5: Site Justification | C5: Site Justification: <Add site address>Of the ## site metrics evaluated on the scorecard, this site has ## green (happy path) and ## yellow (medium risk). Data based on 1500 orders per day. <Enter reason why the site has been selected> | D5: TM
B6: Category | C6: Metric | D6: Sub Category/Additional Notes | E6: Input | F6: Input Category | G6: Green Critieria | H6: Yellow Criteria | I6: Red Criteria | J6: Risk Indicator | K6: Commentary (Please enter bridge if risk is Yellow/Red) | L6: Input Owner | M6: If risk indicator is red or yellow, enter bridge in column K
B7: Financials | C7: PDC (12PM) | D7: 10-Minute | F7: % | G7: 10-Min PDC >= 0.031% | H7: 10 Min >= 0.015% And | J7: =IF(E7>=0.031%,"Green",IF(AND(E7>=0.015%,E8>=0.031%),"Yellow","Red")) -> Red | L7: Topology
D8: 20-Minute | F8: % | H8: 20-Min >= 0.031% | L8: Topology
C9: Drive Time To Centroid (12 PM) | D9: NA | F9: Minutes | G9: <= 6 Minutes | H9: Between 6-10 Minutes | J9: =IF(E9<=6,"Green",IF(E9<10,"Yellow","Red")) -> Green | L9: Topology
C10: How many packages per day does the design allow? (Enter whole number) | D10: NA | F10: Dropdown | G10: 1500 | H10: 1k-1499 | J10: =IF(E10=1500,"Green",IF(E10>1000,"Yellow","Red")) -> Red | L10: Design
C11: SqFt | D11: NA | F11: Sq. Ft | G11: 2.4k-5k | H11: 5k to 10k | J11: =IF(E11<5001,"Green",IF(E11>10000,"Red","Yellow")) -> Green | L11: RE TM
C12: Rent | D12: At or below the market comp average? | F12: Dropdown | G12: Yes | H12: No | J12: =IF(E12="Yes","Green","Yellow") -> Yellow | L12: RE TM
C13: Asking Rent | D13: NA | F13: $ | G13: <=200k/yr | H13: > 200k/yr | J13: =IF(E13<=200000,"Green","Yellow") -> Green | L13: RE TM
C14: Estimated Construction/Startup Cost | D14: With Contingency | E14: ='CAR Approval Page 0'!L9 -> 0 | F14: $ | G14: <=300k/yr | H14: >300k/y | I14: >400k/y | J14: =IF(E14<=300000,"Green",IF(E14<400000,"Yellow","Red")) -> Green | K14: If yellow, provide high level drivers of what is raising the cost here. | L14: PreCon ROM
C15: Estimated Construction/Startup Cost | D15: Without Contingency | E15: ='CAR Approval Page 0'!M9 -> 0 | F15: $ | G15: NA | H15: NA | I15: NA | J15: NA* | L15: PreCon ROM
C16: Estimated Construction/Startup Cost | D16: With Contingency - TI | E16: ='CAR Approval Page 0'!L9-'Site Selection Scorecard'!C3 -> 0 | G16: NA | H16: NA | I16: NA | J16: NA*
C17: Estimated Construction/Startup Cost | D17: Without Contingency - TI | E17: =E15-C3 -> 0 | F17: $ | G17: NA | H17: NA | I17: NA | J17: NA* | L17: PreCon ROM
A18: Pull from the modified by Dennis version | B18: Site Conditions | C18: Bathroom | D18: NA | F18: Dropdown | G18: >=1 functioning unisex stall (shared or non-shared) | H18: >=1 unisex stall, requires upgrade (shared or non-shared) | J18: =IF(E18=">= 1 functioning unisex stall (Shared or non-shared), no upgrade required that is ADA Compliant.","Green","Yellow") -> Yellow | L18: PreCon
C19: Parking | D19: NA | F19: NA | G19: >=6 designated surface stalls | H19: <6 designated stalls in surface lot or parking garage | J19: =IF(E19>=6,"Green","Yellow") -> Yellow | L19: PreCon
C20: Power | D20: NA | F20: Dropdown | G20: >=400A | H20: >= 200 A, 3 phase, or TBD | J20: =IF(E20=">=400 Amp 3 phase 480/208","Green","Yellow") -> Yellow | L20: PreCon
C21: HVAC | D21: NA | F21: Dropdown | G21: Adequate | H21: Not adequate but can be remediated with reasonable cost | J21: =IF(E21="Adequate; 10 tons per 5k sq feet ","Green","Yellow") -> Yellow | L21: PreCon
C22: Flooring | D22: NA | F22: Dropdown | G22: Not permeable | H22: Permeable but can be remediated with reasonable cost | J22: =IF(E22="Non Permeable","Green","Yellow") -> Yellow | L22: PreCon
B23: Customer Facing | C23: Requires Customer Facing Element | D23: NA | F23: Dropdown | G23: No | H23: Yes | J23: =IF(E23="No","Green","Yellow") -> Yellow | L23: PreCon
B24: Operational - Alcohol Risk | C24: Alcohol Sales Restrictions | D24: NA | F24: Dropdown | G24: No Restrictions | H24: Partial Restrictions | I24: Completely Restricted | J24: =IF(E24="No Restrictions","Green",IF(E24="Partial Restrictions","Yellow","Red")) -> Red | L24: TM
B25: Operating - Safety | C25: GRSA Score | D25: NA | F25: Dropdown | G25: NA | H25: NA | I25: NA | J25: =IF(E25="Moderate","Yellow",IF(E25="Low","Green","Red")) -> Red | L25: TM
B26: Operating - Zoning | C26: Zoning Risk | D26: NA | F26: Dropdown | G26: Zoning Permits | H26: Likely Permits QC Use | I26: QC use permitted with Modifications. | J26: =IF(E26="Likely Permits QC Use","Yellow",IF(E26="Zoning Permits","Green","Red")) -> Red | L26: TM
B27: Operating - WHS DD | C27: Environmental Risk | D27: NA | F27: Dropdown | G27: Low Risk (no known/potential life safety issues) | H27: Medium Risk (potential life safety / health risk) | J27: =IF(E27="Low Risk (no known/potential life safety issues)","Green","Yellow") -> Yellow | L27: TM
B28: Operating - WHS Safety | C28: Safety Risk | D28: NA | F28: Dropdown | G28: Meets safety requirements | H28: Does not meet safety requirements but can be brought into compliance with reasonable cost | J28: =IF(E28="Meets safety requirements","Green","Yellow") -> Yellow | L28: TM
B29: Operating - Other Tenant Exclusives | C29: Restrictions on specific ASINS | D29: NA | F29: Dropdown | G29: No tenant exclusives | H29: Existing tenant exclusives with restrictions that are acceptable to Amazon | J29: =IF(E29="No tenant exclusives","Green","Yellow") -> Yellow | L29: TM
J30: *NA indicates the item is not to be included in the field count summary
B31: Scorecard
B32: Total Field Count | C32: =COUNTIF($J$7:$J$29,"Green")+COUNTIF($J$7:$J$29,"Yellow")+COUNTIF($J$7:$J$29,"Red") -> 19
B33: Total Green Fields | C33: =COUNTIFS($J$7:$J$29,"Green") -> 4
B34: Total Yellow Fields | C34: =COUNTIF($J$7:$J$29,"Yellow") -> 10
B35: Total Red Fields | C35: =COUNTIF($J$7:$J$29,"Red") -> 5

Sheet CAR Approval Page 0
C2: ZCL2 - Quick Commerce | O2: Please fill out commentary on any fields showing red or yellow fields in page 0.
C3: Total Amazon Commitment shown in Millions ($USD) | F3: DD & Design | G3: Real Estate | I3: Construction | K3: Startup | M3: Total Request | N3: Total Spent
F4: Capex | G4: Lease Approved | H4: Opex | I4: Capex | J4: Opex | K4: Capex | L4: Opex
B5: 1 | C5: Previously Approved Funding | F5: =SUMIFS('Cost Estimation'!$I$5:$I$101,'Cost Estimation'!$F$5:$F$101,"CAPEX",'Cost Estimation'!$G$5:$G$101,"Yes",'Cost Estimation'!$E$5:$E$101,"DD & Design")+SUMIFS('Cost Estimation'!$K$5:$K$101,'Cost Estimation'!$F$5:$F$101,"CAPEX",'Cost Estimation'!$G$5:$G$101,"Yes",'Cost Estimation'!$E$5:$E$101,"DD & Design") -> 0 | G5: 0 | H5: 0 | I5: =SUMIFS('Cost Estimation'!$I$5:$I$101,'Cost Estimation'!$F$5:$F$101,"CAPEX",'Cost Estimation'!$G$5:$G$101,"Yes",'Cost Estimation'!$E$5:$E$101,"Construction")+SUMIFS('Cost Estimation'!$K$5:$K$101,'Cost Estimation'!$F$5:$F$101,"CAPEX",'Cost Estimation'!$G$5:$G$101,"Yes",'Cost Estimation'!$E$5:$E$101,"Construction") -> 0 | J5: =SUMIFS('Cost Estimation'!$I$5:$I$101,'Cost Estimation'!$F$5:$F$101,"OPEX",'Cost Estimation'!$G$5:$G$101,"Yes",'Cost Estimation'!$E$5:$E$101,"Construction")+SUMIFS('Cost Estimation'!$K$5:$K$101,'Cost Estimation'!$F$5:$F$101,"OPEX",'Cost Estimation'!$G$5:$G$101,"Yes",'Cost Estimation'!$E$5:$E$101,"Construction") -> 0 | K5: =SUMIFS('Cost Estimation'!$I$5:$I$101,'Cost Estimation'!$F$5:$F$101,"CAPEX",'Cost Estimation'!$G$5:$G$101,"Yes",'Cost Estimation'!$E$5:$E$101,"Startup")+SUMIFS('Cost Estimation'!$K$5:$K$101,'Cost Estimation'!$F$5:$F$101,"CAPEX",'Cost Estimation'!$G$5:$G$101,"Yes",'Cost Estimation'!$E$5:$E$101,"Startup") -> 0 | L5: =SUMIFS('Cost Estimation'!$I$5:$I$101,'Cost Estimation'!$F$5:$F$101,"OPEX",'Cost Estimation'!$G$5:$G$101,"Yes",'Cost Estimation'!$E$5:$E$101,"Startup")+SUMIFS('Cost Estimation'!$K$5:$K$101,'Cost Estimation'!$F$5:$F$101,"OPEX",'Cost Estimation'!$G$5:$G$101,"Yes",'Cost Estimation'!$E$5:$E$101,"Startup") -> 0 | M5: - | N5: =SUM(F5:L5) -> 0
B6: =B5+1 -> 2 | C6: Current Request (minus Previously Approved Funding) | F6: 0 | G6: ='Cash Flow'!D41 -> 247734.9 | H6: ='Cash Flow'!E41 -> 0 | I6: =IF('Cost Estimation'!R10=0,"OP Figures",'Cost Estimation'!R10) -> OP Figures | J6: 0 | K6: =IF('Cost Estimation'!R12=0,"OP Figures",'Cost Estimation'!R12) -> OP Figures | L6: 0 | M6: =SUM(F6:L6) -> 247734.9 | N6: -
B7: =B6+1 -> 3 | C7: Total Project Cost | F7: =SUM(F5:F6) -> 0 | G7: =SUM(G5:G6) -> 247734.9 | H7: =SUM(H5:H6) -> 0 | I7: =SUM(I5:I6) -> 0 | J7: =SUM(J5:J6) -> 0 | K7: =SUM(K5:K6) -> 0 | L7: =SUM(L5:L6) -> 0 | M7: =SUM(M5:M6) -> 247734.9 | N7: =SUM(N5:N6) -> 0
B8: =B7+1 -> 4 | C8: Tenant Improvement Allowance: (Use whole numbers; Do not use cost per sq ft.) | F8: ='Cash Flow'!G33 -> 0
B9: =B8+1 -> 5 | C9: Key Metrics: | E9: Payback: (6 UPO) | F9: FA Input | G9: Total Capex (DD & Design, Construction & Startup) - TI | I9: =IFERROR(M9-F8,"") -> 0 | K9: Total Capex (DD & Design, Construction & Startup) | M9: ='Cost Estimation'!R15 -> 0
B10: =B9+1 -> 6 | C10: Site Justification | O10: Section Owner: | P10: Launch Manager
B11: =B10+1 -> 7 | P11: Input from RE, PCM, CM, and TM
B12: =B11+1 -> 8 | C12: Site Details | I12: Site Details Commentary | M12: Description of Landlord Work (If Applicable) | O12: Section Owner: | P12: Transaction Manager
B13: =B12+1 -> 9 | C13: Business Unit | G13: Quick Commerce | I13: The subject site is a 7700 suite wthin a a multi-tenant building. The other uses within the buidling are compatible industrial/commercial uses. Since October 2025, Real Estate has surveyed over a dozen sites. This site offers suffient power to launch the facility, and the landlord will install additional power, bringing the site to 400A 3-phase total power, by December 2026. Sites of with the appropriate zoning, parking, power and other requirements are extremely limited within the service area for this centroid. Replacing this site would be difficult.
B14: =B13+1 -> 10 | C14: Site Code | G14: ZCL2
B15: =B14+1 -> 11 | C15: Site Address (Full Address w/City & State) | G15: ='Cash Flow'!D4 -> 4353 Cranwood Parkway, Cleveland, OH, Cleveland Ohio
B16: =B15+1 -> 12 | C16: Building Type/Former Use | G16: Industrial Warehouse
B17: =B16+1 -> 13 | C17: Launch Type | G17: New Launch
B18: =B17+1 -> 14 | C18: City/MSA | G18: Cleveland, OH
B19: =B18+1 -> 15 | C19: # of available parking spots | G19: 10
B20: =B19+1 -> 16 | C20: Building Square Footage | G20: ='Cash Flow'!E8 -> 7700
B21: =B20+1 -> 17 | C21: Transaction Type | G21: Lease
B22: =B21+1 -> 18 | C22: How many Packages per day does the design allow? | G22: This site has a maximum capacity of 7500 units per day. With 6 units per order (UPO), site can handle capacity of 1250 orders per day. | P22: Design
B23: =B22+1 -> 19 | C23: Does Site Require Customer Facing Element?
B24: =B23+1 -> 20 | C24: Financial Analysis ($MM) | I24: Commentary (Please enter bridge if appropriate) | O24: Section Owner: | P24: Finance
B25: =B24+1 -> 21 | C25: Hurdle Rate | G25: 0.17
B26: =B25+1 -> 22 | C26: 5 YR NPV
B27: =B26+1 -> 23 | C27: Amount of Current SU Request included in OP SU estimate ( % / $MM ) | G27: Over 100% | H27: 200 | P27: Doug Richardson/Scott Sawrey (Finance)
B28: =B27+1 -> 24 | C28: Amount of Total Project Cost included in OP Total Project estimate ( % / $MM ) | G28: Over 100% | H28: 200 | P28: Doug Richardson/Scott Sawrey (Finance)
B29: =B28+1 -> 25 | C29: Real Estate Summary and Agreement Details | G29: Site | I29: Commentary (Please enter bridge if appropriate) | O29: Section Owner: | P29: TM
B30: =B29+1 -> 26 | C30: Lease Term (Years) | G30: 5
B31: =B30+1 -> 27 | C31: Forecast Lease Start Date | G31: ='Cash Flow'!E20 -> 46235
B32: =B31+1 -> 28 | C32: Forecast Lease End Date | G32: =G31+60 -> 46295
B33: =B32+1 -> 29 | C33: Extension Options: # and FMV or Fixed Rate | G33: 3 | I33: Three renewals for five years each, at FRM.
B34: =B33+1 -> 30 | C34: Year 1 Base Rent PSF | G34: ='Cash Flow'!I10 -> 6.06 | I34: Describe median and avg. rent comps here.
B35: =B34+1 -> 31 | C35: Annual Rent Increases | G35: ='Cash Flow'!E10 -> 0.03
B36: =B35+1 -> 32 | C36: OPEX | G36: ='Cash Flow'!E11 -> 0
B37: =B36+1 -> 33 | C37: OPEX estimated annual increase | G37: ='Cash Flow'!E18 -> 0.02
B38: =B37+1 -> 34 | C38: Year 1 Total Gross Rent PSF | G38: ='Cash Flow'!P48 -> 6.06
B39: =B38+1 -> 35 | C39: Tenant Improvement Allowance ($) | G39: ='Cash Flow'!G33 -> 0
B40: =B39+1 -> 36 | C40: Rent at or below market average?
B41: =B40+1 -> 37 | C41: Total Gross Yr 1 Annual Rent (Target below 200k) | G41: ='Cash Flow'!N48 -> 46662
B42: =B41+1 -> 38 | C42: Was the QC Addendum Used? | G42: No | I42: Used Amazon lease form
B43: =B42+1 -> 39 | C43: Topology | G43: Site | I43: Commentary/Topology Summary (Please enter bridge if appropriate) | O43: Section Owner: | P43: Topology
B44: =B43+1 -> 40 | C44: 25-minute PDC - 12PM | G44: 0.0019 | I44: Selected site is 16.17 min (12pm) from the University Heights demand center. Gopuff serves this demand center with a faster speed 11.75 min (12pm). The 2026 topology plan for the Cleveland metro is a 1-pin setup. See topology map tab for details.
B45: =B44+1 -> 41 | C45: Transit time to Ideal Centroid - 12PM | G45: 16.17
B46: =B45+1 -> 42 | C46: Transit time to Ideal Centroid - 5PM | G46: 18.83
B47: =B46+1 -> 43 | C47: Distance to Ideal Centroid | G47: 5.9
B48: =B47+1 -> 44 | C48: Zoning/Operational Risk Assessment | G48: Risk Rating | H48: Commentary/Summary/Bridge (Please enter bridge if red/yellow) | O48: Section Owner: | P48: Multiple
B49: =B48+1 -> 45 | C49: Zoning Risk Assessment | G49: Green | H49: Wholesale is permitted/by-right. Retail sales ancillary to wholesale businesses are permitted. Storage and distribution of packaged goods is permitted/by-right. | P49: Econ Dev
B50: =B49+1 -> 46 | C50: Jurisdictional Risk Assessment | G50: Green | H50: Low-risk/Green. Zoning allows both distribution/wholesale and retail (if ancillary to wholesale). No adjacent residential. Project site is located within an industrial node; no adjacent residential. | P50: EDP - Geographic lead
B51: =B50+1 -> 47 | C51: Ergonomic Safety Review | G51: Yellow | H51: Medium-Low risk. Ergonomic risk dependent on implementation of tech weight filter, approved bin drawer solution, and cart selection. Global Ergonomics is working with QC team as design develops; site-specific assessments to follow. | P51: CAR Approval Manager
B52: =B51+1 -> 48 | C52: WHS Safety Risk (Parking, associate safety, ADA compliance etc.) | G52: Green | H52: Low risk based on WHS FEC fully approved condition in approvals correspondence from 3/19/2026. | P52: TM/CAR Approval Manager
B53: =B52+1 -> 49 | C53: WHS environmental Risk assessment | G53: Yellow | H53: Medium Risk - Site is located in a primarily industrial and commercial area with a history of nearby hazardous substance releases which may have migrated onsite potentially affecting subsurface medias. - Vapor intrusion is not suspected to be an issue and sampling is not required. - Soil contamination possible; construction team will need to disclose site conditions to the general contractor. General contractor will be responsible for health and safety and soil management according to the Amazon WHS DD Soil Management SOP. - Building constructed by 1970; hazardous building materials possible. | P53: TM
B54: =B53+1 -> 50 | C54: Permit Contingency Details | G54: Green | H54: There is a 90 day permit contingency. If exercised, Tenant must pay landlord up to $12,000 in LL's out of pocket costs. | P54: TM
B55: =B54+1 -> 51 | C55: Early Termination Right | G55: Red | H55: No early termination option available.
B56: =B55+1 -> 52 | C56: Any LL requirements that add Risk | G56: Green | H56: None | P56: TM
B57: =B56+1 -> 53 | C57: Operational Risk Call outs? | G57: Green | H57: None | P57: TM
B58: =B57+1 -> 54 | C58: Alcohol Assessment | H58: Enter Details | P58: TM with support from Legal
B59: =B58+1 -> 55 | C59: Tenant Exclusives: Restrictions on specific ASINs | G59: No tenant exclusives | H59: None
B60: =B59+1 -> 56 | C60: Preconstruction Cost and Building Condition Summary | G60: Risk Rating/Category | I60: Commentary/Summary/Bridge (Please enter bridge if red/yellow) | O60: Section Owner: | P60: Precon
B61: =B60+1 -> 57 | C61: Construction/SU CAPEX Cost | E61: =L9 -> 0 | G61: Main CAPEX Driver | I61: Please input main CAPEX drivers in cost estimation summary; this field always requires input | P61: Construction Field.
B62: =B61+1 -> 58 | C62: Permit Risk Assessment
B63: =B62+1 -> 59 | C63: Bathroom; ADA Compliance
B64: =B63+1 -> 60 | C64: Existing Building Conditions Narrative | I64: Summarize
B65: =B64+1 -> 61 | C65: Cost Estimation Basis
B66: =B65+1 -> 62 | C66: Power Assessment Narrative | I66: Enter Power Assessment Narrative.
B67: =B66+1 -> 63 | C67: HVAC Risk Narrative | I67: Please add age and condition of existing equipment
B68: =B67+1 -> 64 | C68: Food Safe Finishes (Flooring/Walls/Ceiling)
B69: =B68+1 -> 65 | C69: Design Stage
B70: =B69+1 -> 66 | C70: Timeline Risks
B71: =B70+1 -> 67 | C71: Budget Confidence Assessment
B72: =B71+1 -> 68 | C72: Demolition
B73: =B72+1 -> 69 | C73: Potential Timeline Risks | I73: Summary of any risks that could delay all or portion of launch, ex: not enough power, alcohol permits, food safety permits, etc

Sheet FA Inputs
B2: SECTION | C2: FIELD | D2: INPUT | E2: required? | F2: Notes
B3: Site Detail | C3: Use Case (Feasibility or CAR) | D3: Feasibility | E3: Y
B4: Site Detail | C4: Site Code | D4: ='Site Selection Scorecard'!C1 -> 0 | E4: Y
B5: Site Detail | C5: Launch Date | D5: 46054 | E5: Y | F5: for launches before Jan 2026, enter launch date 01/01/26
B6: Capital Investment | C6: Construction Capex | D6: ='CAR Approval Page 0'!I7 -> 0 | E6: Y
B7: Capital Investment | C7: Start Up Capex | D7: ='CAR Approval Page 0'!K7 -> 0
B8: Capital Investment | C8: Design & DD Capex | D8: ='CAR Approval Page 0'!F7 -> 0
B9: Capital Investment | C9: Startup (OPEX Only) | D9: ='CAR Approval Page 0'!L7 -> 0
B10: Lease Obligation & Details | C10: Lease start date | D10: ='CAR Approval Page 0'!G31 -> 46235 | E10: Y
B11: Lease Obligation & Details | C11: Lease end date | D11: ='CAR Approval Page 0'!G32 -> 46295 | E11: Y
B12: Lease Obligation & Details | C12: Lease term (months) | D12: =DATEDIF(D10,D11,"m")+1 -> 2 | F12: formula
B13: Lease Obligation & Details | C13: TIA? (y/n) | D13: no
B14: Lease Obligation & Details | C14: TI (tenent improvement allowance) | D14: ='Site Selection Scorecard'!C3 -> 0
B15: Lease Obligation & Details | C15: Base rent per sqft | D15: ='CAR Approval Page 0'!G34 -> 6.06 | E15: Y | F15: Guardrails only
B16: Lease Obligation & Details | C16: Annual Rent Increase | D16: ='CAR Approval Page 0'!G35 -> 0.03 | E16: Y | F16: Guardrails only
B17: Lease Obligation & Details | C17: Lease opex per sqft | D17: ='CAR Approval Page 0'!G36 -> 0 | E17: Y | F17: Guardrails only
B18: Lease Obligation & Details | C18: Annual est Opex Increase | D18: ='CAR Approval Page 0'!G37 -> 0.02 | E18: Y | F18: Guardrails only
B19: Lease Obligation & Details | C19: Total building sqft | D19: ='CAR Approval Page 0'!G38 -> 6.06 | E19: Y
B20: Topology | C20: mechanical capacity (orders per day) | D20: ='Site Selection Scorecard'!E10 -> 0 | E20: Y
B21: Topology | C21: 20-minute PDC - 12pm | D21: ='Site Selection Scorecard'!E8 -> 0 | E21: Y
B22: Alcohol | C22: Alcohol? (y/n) | D22: no | E22: Y
B23: Alcohol | C23: Alcohol launch date | F23: first date of alcohol availability

Sheet Topology Map
U1: Black Triangle: Selected Sites
U2: Green Triangle: Ideal Pin
U3: Purple Cross: Gopuff

Sheet Dropdowns (Hidden)
A1: Page 0 Dropdowns
A2: General | B2: General | C2: General | D2: General | E2: Precon | F2: Precon | G2: Precon | H2: Precon | I2: Precon | J2: Precon
A3: Launch Type | B3: Transaction Type | C3: Y/N Dropdown | D3: G/Y/R | E3: Cost Estimation Basis | F3: Power Assessment | G3: HVAC Assessment | H3: Design Stage | I3: Timeline Risks | J3: Budget Confidence Assessment
A4: New Launch | B4: Lease | C4: Yes | D4: Green | E4: Precon ROM | F4: Power is adequate | G4: 1 Ton available per 400 sq ft. | H4: No drawing | I4: Permit Issues | J4: P2 Estimate - Final GMP
A5: Retrofit | B5: Own | C5: No | D5: Yellow | E5: GC Validated | F5: Power Risk | G5: <1 Ton per 400 sq ft | H5: Survey | I5: Power Upgrade Required | J5: P1 Estimate - CBRE Vendor ROM
A6: Expansion | B6: 3P | D6: Red | E6: GC Budget | F6: Requires engineering | G6: No HVAC provided | H6: Amazon Test Fit | I6: Leadtimes for equipment | J6: P0 Estimate - Site Selection Checklist
A7: Initiative | E7: PC Rom + no drawing | H7: Schematic Design | I7: No known Risks
A8: Lease Renewal | H8: Construction Documents | I8: Other/Please Define
H9: No Survey
H10: No Survey; No Drawing
H11: Survey; Amazon Test Fit
A24: Scorecard Dropdowns
A25: Rent | B25: Bathroom | C25: Power | D25: HVAC | E25: Flooring | F25: Zoning Risk | G25: Environmental Risk | H25: Safety Risk | I25: Restrictions on specific ASINS | J25: GSRA Risk Scoring | K25: Alcohol Restrictions | L25: Demolition
A26: Yes | B26: Existing ADA Restroom does not require modifications | C26: >=400A (Or Amp appropriate for Orders Per Day Volume), 3 phase. No panel modifications required | D26: Adequate; 10 tons per 5k sq feet | E26: Not permeable | F26: Zoning Permits | G26: Low Risk (no known/potential life safety issues) | H26: Meets safety requirements | I26: No tenant exclusives | J26: Critical | K26: No Restrictions | L26: No
A27: No | B27: Existing restroom modifications required to make ADA compliant. | C27: >=400A (Or Amp appropriate for Orders Per Day Volume), 3 Phase. Modifications required | D27: Not adequate but can be remediated with reasonable cost | E27: Permeable but can be remediated with reasonable cost | F27: Likely Permits QC Use | G27: Medium Risk (potential life safety / health risk) | H27: Does not meet safety requirements but can be brought into compliance with reasonable cost | I27: Existing tenant exclusives with restrictions that are acceptable to Amazon | J27: Very High | K27: Partial Restrictions | L27: Yes
B28: No existing restroom/extensive modifications required | C28: <400A (Amp not appropriate for Orders Per Day Volume), 3 Phase. | E28: Requires new finishes | F28: QC use permitted with Modifications. | J28: High | K28: Completely Restricted | L28: Extensive Demolition/Patchback work
J29: Moderate
J30: Low
A35: ROM Dropdown
A36: Y/N | B36: Team | C36: CAPEX/OPEX
A37: Yes | B37: Construction | C37: CAPEX
A38: No | B38: Startup | C38: OPEX
B39: DD & Design

Sheet Cash Flow
B2: MR/SPEC: UPDATE IN GREEN CELLS ONLY
B4: Address | D4: 4353 Cranwood Parkway, Cleveland, OH, Cleveland Ohio
B5: Ownership | D5: CRANWOOD INVESTMENTS, LLC
B7: Lease Terms | G7: Base Rent Schedule
B8: Building Square footage | E8: 7700 | G8: Starting Mo. | H8: Ending Mo. | I8: $ Per SF (Annual)
B9: Starting Base Rent (PSF) | E9: 6.06 | G9: =IF(H9=0,0,1) -> 0 | H9: =E22 -> 0 | I9: 0
B10: Base Rent Increases | E10: 0.03 | G10: =H9+1 -> 1 | H10: 12 | I10: =E9 -> 6.06
B11: Starting OpEx (PSF) | E11: =IFERROR((IFERROR(INDEX(G71:G88,MATCH(TRUE,INDEX((G71:G88<>0),0),0)),0)+IFERROR(INDEX(F71:F88,MATCH(TRUE,INDEX((F71:F88<>0),0),0)),0)+H71)*12/E8,0) -> 0 | F11: =IFERROR(IF((E11/E9)<25%,"ALERT","OK")," ") -> ALERT | G11: =IF(H10<$E$21,IF(H10>1,(H10+1),""),"") -> 13 | H11: =IF(G11="","",IF(G11+11>$E$21,$E$21,G11+11)) -> 24 | I11: =IF(H11<>"",(I10*(1+$E$10)),0) -> 6.2418
B12: CAM | G12: =IF(H11<$E$21,IF(H11>1,(H11+1),""),"") -> 25 | H12: =IF(G12="","",IF(G12+11>$E$21,$E$21,G12+11)) -> 36 | I12: =IF(H12<>"",(I11*(1+$E$10)),0) -> 6.429054
B13: Insurance | G13: =IF(H12<$E$21,IF(H12>1,(H12+1),""),"") -> 37 | H13: =IF(G13="","",IF(G13+11>$E$21,$E$21,G13+11)) -> 48 | I13: =IF(H13<>"",(I12*(1+$E$10)),0) -> 6.6219256
B14: Taxes | G14: =IF(H13<$E$21,IF(H13>1,(H13+1),""),"") -> 49 | H14: =IF(G14="","",IF(G14+11>$E$21,$E$21,G14+11)) -> 60 | I14: =IF(H14<>"",(I13*(1+$E$10)),0) -> 6.8205834
D15: Contingency % | E15: 0.2 | G15: =IF(H14<$E$21,IF(H14>1,(H14+1),""),"") | H15: =IF(G15="","",IF(G15+11>$E$21,$E$21,G15+11)) | I15: =IF(H15<>"",(I14*(1+$E$10)),0) -> 0
B16: 0 | C16: Base Rent | D16: Prop Mgmt Fee | E16: =IFERROR((INDEX(G71:G88,MATCH(TRUE,INDEX((G71:G88<>0),0),0))/E8)*12,0) -> 0 | G16: =IF(H15<$E$21,IF(H15>1,(H15+1),""),"") | H16: =IF(G16="","",IF(G16+11>$E$21,$E$21,G16+11)) | I16: =IF(H16<>"",(I15*(1+$E$10)),0) -> 0
B17: 0 | C17: Base Rent | D17: Rent Tax | E17: =IFERROR((INDEX(F71:F88,MATCH(TRUE,INDEX((F71:F88<>0),0),0))/E8)*12,0) -> 0 | G17: =IF(H16<$E$21,IF(H16>1,(H16+1),""),"") | H17: =IF(G17="","",IF(G17+11>$E$21,$E$21,G17+11)) | I17: =IF(H17<>"",(I16*(1+$E$10)),0) -> 0
B18: Annual OPEX Increases | E18: 0.02 | G18: =IF(H17<$E$21,IF(H17>1,(H17+1),""),"") | H18: =IF(G18="","",IF(G18+11>$E$21,$E$21,G18+11)) | I18: =IF(H18<>"",(I17*(1+$E$10)),0) -> 0 | M18: e
B19: OPEX Increases Occur (1/1/next year) | E19: =IF(E20="","",DATE(YEAR(--E20)+1,1,1)) -> 46388 | G19: =IF(H18<$E$21,IF(H18>1,(H18+1),""),"") | H19: =IF(G19="","",IF(G19+11>$E$21,$E$21,G19+11)) | I19: =IF(H19<>"",(I18*(1+$E$10)),0) -> 0
B20: Lease Commencement | E20: 46235 | G20: =IF(H19<$E$21,IF(H19>1,(H19+1),""),"") | H20: =IF(G20="","",IF(G20+11>$E$21,$E$21,G20+11)) | I20: =IF(H20<>"",(I19*(1+$E$10)),0) -> 0
B21: Term (Months) | E21: 60 | G21: =IF(H20<$E$21,IF(H20>1,(H20+1),""),"") | H21: =IF(G21="","",IF(G21+11>$E$21,$E$21,G21+11)) | I21: =IF(H21<>"",(I20*(1+$E$10)),0) -> 0
B22: Free Rent (Months) | E22: 0 | G22: =IF(H21<$E$21,IF(H21>1,(H21+1),""),"") | H22: =IF(G22="","",IF(G22+11>$E$21,$E$21,G22+11)) | I22: =IF(H22<>"",(I21*(1+$E$10)),0) -> 0
B23: Termination Option (Month?) | E23: 0 | G23: =IF(H22<$E$21,IF(H22>1,(H22+1),""),"") | H23: =IF(G23="","",IF(G23+11>$E$21,$E$21,G23+11)) | I23: =IF(H23<>"",(I22*(1+$E$10)),0) -> 0
B24: Termination Fee (Inc. Un-Amot TI/Fees) | E24: 0 | G24: =IF(H23<$E$21,IF(H23>1,(H23+1),""),"") | H24: =IF(G24="","",IF(G24+11>$E$21,$E$21,G24+11)) | I24: =IF(H24<>"",(I23*(1+$E$10)),0) -> 0
B25: Termination Fee Notes | E25: n/a | G25: =IF(H24<$E$21,IF(H24>1,(H24+1),""),"") | H25: =IF(G25="","",IF(G25+11>$E$21,$E$21,G25+11)) | I25: =IF(H25<>"",(I24*(1+$E$10)),0) -> 0
B26: Tenant Improvement $/SF | E26: 0 | G26: =IF(H25<$E$21,IF(H25>1,(H25+1),""),"") | H26: =IF(G26="","",IF(G26+11>$E$21,$E$21,G26+11)) | I26: =IF(H26<>"",(I25*(1+$E$10)),0) -> 0
G27: =IF(H26<$E$21,IF(H26>1,(H26+1),""),"") | H27: =IF(G27="","",IF(G27+11>$E$21,$E$21,G27+11)) | I27: =IF(H27<>"",(I26*(1+$E$10)),0) -> 0
G28: =IF(H27<$E$21,IF(H27>1,(H27+1),""),"") | H28: =IF(G28="","",IF(G28+11>$E$21,$E$21,G28+11)) | I28: =IF(H28<>"",(I27*(1+$E$10)),0) -> 0
G29: =IF(H28<$E$21,IF(H28>1,(H28+1),""),"") | H29: =IF(G29="","",IF(G29+11>$E$21,$E$21,G29+11)) | I29: =IF(H29<>"",(I28*(1+$E$10)),0) -> 0
B31: Tenant Improvement Allowances
D32: TI Included in Base Rent | E32: Additional Amortized TI Bucket 1 | F32: Additional Amortized TI Bucket 2 | G32: Total TI Funds Available | I32: Total Development Budget | K32: Capital Required
B33: Principal | D33: =E26*E8 -> 0 | G33: =E33+D33+F33 -> 0 | K33: =MAX(0,I33-F33-E33-D33) -> 0
B34: Term
B35: Interest Rate
B36: Monthly Payment | E36: =IFERROR(PMT(E35/12,E34,-E33,0),0) -> 0 | F36: =IFERROR(PMT(F35/12,F34,-F33,0),0) -> 0
C37: Month Amortized TI Starts
B39: Entire Lease Obligation
D40: Base Rent | E40: Operating Expenses | F40: Amortized TI Bucket 1 | H40: Amortized Bucket 2 | I40: Out of Pocket TI | K40: Total Obligation
C41: Totals | D41: =SUMIF(E71:E310,"<"&99^"99") -> 247734.9 | E41: =SUMIF(I71:J310,"<"&99^"99") -> 0 | F41: =SUMIF(K71:K310,"<"&99^"99") -> 0 | H41: =SUMIF(L71:M310,"<"&99^"99") -> 0 | I41: =K33 -> 0 | K41: =I41+H41+F41+E41+D41 -> 247734.9
C42: Monthly Average | D42: =D41/$E$21 -> 4128.9149 | E42: =E41/$E$21 -> 0 | F42: =F41/$E$21 -> 0 | H42: =H41/$E$21 -> 0 | K42: =K41/$E$21 -> 4128.9149
C43: Annual Average per SF | D43: =+D42/E8*12 -> 6.4346726 | E43: =+E42/E8*12 -> 0 | F43: =+F42/E8*12 -> 0 | H43: =+H42/E8*12 -> 0 | K43: =+K42/E8*12 -> 6.4346726
B44: 0.12 | C44: ="NPV ("&B44*100&"%)" -> NPV (12%) | D44: =NPV((1+$B$44)^(1/12)-1,OFFSET(E71:E310,0,0,COUNT(E71:E310),1)) -> 186975.95 | E44: =NPV((1+$B$44)^(1/12)-1,OFFSET(I71:I310,0,0,COUNT(I71:I310),1)) -> 0 | F44: =NPV((1+$B$44)^(1/12)-1,OFFSET(K71:K310,0,0,COUNT(K71:K310),1)) -> 0 | H44: =NPV((1+$B$44)^(1/12)-1,OFFSET(L71:L310,0,0,COUNT(L71:L310),1)) -> 0 | I44: =I41 -> 0 | K44: =I44+H44+F44+E44+D44 -> 186975.95
B46: Annual Lease Obligation
E47: Annualized Base Rent | F47: Rent Tax | G47: PM Fee | H47: CAM, Tax & Ins | I47: Annualized Operating Expenses | K47: Annualized Amortized TI | L47: Annualized Amortized TI | N47: Annualized Gross Rent | P47: Annualized Gross Rent per SF
C48: Year 1 | E48: =SUMIF(E71:E82,"<"&99^"99") -> 46662 | F48: =SUMIF(F71:F82,"<"&99^"99") -> 0 | G48: =SUMIF(G71:G82,"<"&99^"99") -> 0 | H48: =SUMIF(H71:H82,"<"&99^"99") -> 0 | I48: =SUMIF(I71:I82,"<"&99^"99") -> 0 | K48: =SUMIF(K71:K82,"<"&99^"99") -> 0 | L48: =SUMIF(L71:L82,"<"&99^"99") -> 0 | N48: =SUMIF(N71:N82,"<"&99^"99") -> 46662 | P48: =+N48/$E$8 -> 6.06
C49: Year 2 | E49: =SUMIF(E83:E94,"<"&99^"99") -> 48061.86 | F49: =SUMIF(F83:F94,"<"&99^"99") -> 0 | G49: =SUMIF(G83:G94,"<"&99^"99") -> 0 | H49: =SUMIF(H83:H94,"<"&99^"99") -> 0 | I49: =SUMIF(I83:I94,"<"&99^"99") -> 0 | K49: =SUMIF(K83:K94,"<"&99^"99") -> 0 | L49: =SUMIF(L83:L94,"<"&99^"99") -> 0 | N49: =SUMIF(N83:N94,"<"&99^"99") -> 48061.86 | P49: =+N49/$E$8 -> 6.2418
C50: Year 3 | E50: =SUMIF(E95:E106,"<"&99^"99") -> 49503.716 | F50: =SUMIF(F95:F106,"<"&99^"99") -> 0 | G50: =SUMIF(G95:G106,"<"&99^"99") -> 0 | H50: =SUMIF(H95:H106,"<"&99^"99") -> 0 | I50: =SUMIF(I95:I106, "<"&99^"99") -> 0 | K50: =SUMIF(K95:K106,"<"&99^"99") -> 0 | L50: =SUMIF(L95:L106, "<"&99^"99") -> 0 | N50: =SUMIF(N95:N106, "<"&99^"99") -> 49503.716 | P50: =+N50/$E$8 -> 6.429054
C51: Year 4 | E51: =SUMIF(E107:E118,"<"&99^"99") -> 50988.827 | F51: =SUMIF(F107:F118,"<"&99^"99") -> 0 | G51: =SUMIF(G107:G118,"<"&99^"99") -> 0 | H51: =SUMIF(H107:H118,"<"&99^"99") -> 0 | I51: =SUMIF(I107:I118,"<"&99^"99") -> 0 | K51: =SUMIF(K107:K118,"<"&99^"99") -> 0 | L51: =SUMIF(L107:L118,"<"&99^"99") -> 0 | N51: =SUMIF(N107:N118,"<"&99^"99") -> 50988.827 | P51: =+N51/$E$8 -> 6.6219256
C52: Year 5 | E52: =SUMIF(E119:E130,"<"&99^"99") -> 52518.492 | F52: =SUMIF(F119:F130,"<"&99^"99") -> 0 | G52: =SUMIF(G119:G130,"<"&99^"99") -> 0 | H52: =SUMIF(H119:H130,"<"&99^"99") -> 0 | I52: =SUMIF(I119:I130,"<"&99^"99") -> 0 | K52: =SUMIF(K119:K130,"<"&99^"99") -> 0 | L52: =SUMIF(L119:L130,"<"&99^"99") -> 0 | N52: =SUMIF(N119:N130,"<"&99^"99") -> 52518.492 | P52: =+N52/$E$8 -> 6.8205834
C53: Year 6 | E53: =SUMIF(E131:E142,"<"&99^"99") -> 0 | F53: =SUMIF(F131:F142,"<"&99^"99") -> 0 | G53: =SUMIF(G131:G142,"<"&99^"99") -> 0 | H53: =SUMIF(H131:H142,"<"&99^"99") -> 0 | I53: =SUMIF(I131:I142,"<"&99^"99") -> 0 | K53: =SUMIF(K131:K142,"<"&99^"99") -> 0 | L53: =SUMIF(L131:L142,"<"&99^"99") -> 0 | N53: =SUMIF(N131:N142,"<"&99^"99") -> 0 | P53: =+N53/$E$8 -> 0
C54: Year 7 | E54: =SUMIF(E143:E154,"<"&99^"99") -> 0 | F54: =SUMIF(F143:F154,"<"&99^"99") -> 0 | G54: =SUMIF(G143:G154,"<"&99^"99") -> 0 | H54: =SUMIF(H143:H154,"<"&99^"99") -> 0 | I54: =SUMIF(I143:I154,"<"&99^"99") -> 0 | K54: =SUMIF(K143:K154,"<"&99^"99") -> 0 | L54: =SUMIF(L143:L154,"<"&99^"99") -> 0 | N54: =SUMIF(N143:N154,"<"&99^"99") -> 0 | P54: =+N54/$E$8 -> 0
C55: Year 8 | E55: =SUMIF(E155:E166,"<"&99^"99") -> 0 | F55: =SUMIF(F155:F166,"<"&99^"99") -> 0 | G55: =SUMIF(G155:G166,"<"&99^"99") -> 0 | H55: =SUMIF(H155:H166,"<"&99^"99") -> 0 | I55: =SUMIF(I155:I166,"<"&99^"99") -> 0 | K55: =SUMIF(K155:K166,"<"&99^"99") -> 0 | L55: =SUMIF(L155:L166,"<"&99^"99") -> 0 | N55: =SUMIF(N155:N166,"<"&99^"99") -> 0 | P55: =+N55/$E$8 -> 0
C56: Year 9 | E56: =SUMIF(E167:E178,"<"&99^"99") -> 0 | F56: =SUMIF(F167:F178,"<"&99^"99") -> 0 | G56: =SUMIF(G167:G178,"<"&99^"99") -> 0 | H56: =SUMIF(H167:H178,"<"&99^"99") -> 0 | I56: =SUMIF(I167:I178,"<"&99^"99") -> 0 | K56: =SUMIF(K167:K178,"<"&99^"99") -> 0 | L56: =SUMIF(L167:L178,"<"&99^"99") -> 0 | N56: =SUMIF(N167:N178,"<"&99^"99") -> 0 | P56: =+N56/$E$8 -> 0
C57: Year 10 | E57: =SUMIF(E179:E190,"<"&99^"99") -> 0 | F57: =SUMIF(F179:F190,"<"&99^"99") -> 0 | G57: =SUMIF(G179:G190,"<"&99^"99") -> 0 | H57: =SUMIF(H179:H190,"<"&99^"99") -> 0 | I57: =SUMIF(I179:I190,"<"&99^"99") -> 0 | K57: =SUMIF(K179:K190,"<"&99^"99") -> 0 | L57: =SUMIF(L179:L190,"<"&99^"99") -> 0 | N57: =SUMIF(N179:N190,"<"&99^"99") -> 0 | P57: =+N57/$E$8 -> 0
C58: Year 11 | E58: =SUMIF(E191:E202,"<"&99^"99") -> 0 | F58: =SUMIF(F191:F202,"<"&99^"99") -> 0 | G58: =SUMIF(G191:G202,"<"&99^"99") -> 0 | H58: =SUMIF(H191:H202,"<"&99^"99") -> 0 | I58: =SUMIF(I191:I202,"<"&99^"99") -> 0 | K58: =SUMIF(K191:K202,"<"&99^"99") -> 0 | L58: =SUMIF(L191:L202,"<"&99^"99") -> 0 | N58: =SUMIF(N191:N202,"<"&99^"99") -> 0 | P58: =+N58/$E$8 -> 0
C59: Year 12 | E59: =SUMIF(E203:E214,"<"&99^"99") -> 0 | F59: =SUMIF(F203:F214,"<"&99^"99") -> 0 | G59: =SUMIF(G203:G214,"<"&99^"99") -> 0 | H59: =SUMIF(H203:H214,"<"&99^"99") -> 0 | I59: =SUMIF(I203:I214,"<"&99^"99") -> 0 | K59: =SUMIF(K203:K214,"<"&99^"99") -> 0 | L59: =SUMIF(L203:L214,"<"&99^"99") -> 0 | N59: =SUMIF(N203:N214,"<"&99^"99") -> 0 | P59: =+N59/$E$8 -> 0
C60: Year 13 | E60: =SUMIF(E215:E226,"<"&99^"99") -> 0 | F60: =SUMIF(F215:F226,"<"&99^"99") -> 0 | G60: =SUMIF(G215:G226,"<"&99^"99") -> 0 | H60: =SUMIF(H215:H226,"<"&99^"99") -> 0 | I60: =SUMIF(I215:I226,"<"&99^"99") -> 0 | K60: =SUMIF(K215:K226,"<"&99^"99") -> 0 | L60: =SUMIF(L215:L226,"<"&99^"99") -> 0 | N60: =SUMIF(N215:N226,"<"&99^"99") -> 0 | P60: =+N60/$E$8 -> 0
C61: Year 14 | E61: =SUMIF(E227:E238,"<"&99^"99") -> 0 | F61: =SUMIF(F227:F238,"<"&99^"99") -> 0 | G61: =SUMIF(G227:G238,"<"&99^"99") -> 0 | H61: =SUMIF(H227:H238,"<"&99^"99") -> 0 | I61: =SUMIF(I227:I238,"<"&99^"99") -> 0 | K61: =SUMIF(K227:K238,"<"&99^"99") -> 0 | L61: =SUMIF(L227:L238,"<"&99^"99") -> 0 | N61: =SUMIF(N227:N238,"<"&99^"99") -> 0 | P61: =+N61/$E$8 -> 0
C62: Year 15 | E62: =SUMIF(E239:E250,"<"&99^"99") -> 0 | F62: =SUMIF(F239:F250,"<"&99^"99") -> 0 | G62: =SUMIF(G239:G250,"<"&99^"99") -> 0 | H62: =SUMIF(H239:H250,"<"&99^"99") -> 0 | I62: =SUMIF(I239:I250,"<"&99^"99") -> 0 | K62: =SUMIF(K239:K250,"<"&99^"99") -> 0 | L62: =SUMIF(L239:L250,"<"&99^"99") -> 0 | N62: =SUMIF(N239:N250,"<"&99^"99") -> 0 | P62: =+N62/$E$8 -> 0
C63: Year 16 | E63: =SUMIF(E251:E262,"<"&99^"99") -> 0 | F63: =SUMIF(F251:F262,"<"&99^"99") -> 0 | G63: =SUMIF(G251:G262,"<"&99^"99") -> 0 | H63: =SUMIF(H251:H262,"<"&99^"99") -> 0 | I63: =SUMIF(I251:I262,"<"&99^"99") -> 0 | K63: =SUMIF(K251:K262,"<"&99^"99") -> 0 | L63: =SUMIF(L251:L262,"<"&99^"99") -> 0 | N63: =SUMIF(N251:N262,"<"&99^"99") -> 0 | P63: =+N63/$E$8 -> 0
C64: Year 17 | E64: =SUMIF(E263:E274,"<"&99^"99") -> 0 | F64: =SUMIF(F263:F274,"<"&99^"99") -> 0 | G64: =SUMIF(G263:G274,"<"&99^"99") -> 0 | H64: =SUMIF(H263:H274,"<"&99^"99") -> 0 | I64: =SUMIF(I263:I274,"<"&99^"99") -> 0 | K64: =SUMIF(K263:K274,"<"&99^"99") -> 0 | L64: =SUMIF(L263:L274,"<"&99^"99") -> 0 | N64: =SUMIF(N263:N274,"<"&99^"99") -> 0 | P64: =+N64/$E$8 -> 0
C65: Year 18 | E65: =SUMIF(E275:E286,"<"&99^"99") -> 0 | F65: =SUMIF(F275:F286,"<"&99^"99") -> 0 | G65: =SUMIF(G275:G286,"<"&99^"99") -> 0 | H65: =SUMIF(H275:H286,"<"&99^"99") -> 0 | I65: =SUMIF(I275:I286,"<"&99^"99") -> 0 | K65: =SUMIF(K275:K286,"<"&99^"99") -> 0 | L65: =SUMIF(L275:L286,"<"&99^"99") -> 0 | N65: =SUMIF(N275:N286,"<"&99^"99") -> 0 | P65: =+N65/$E$8 -> 0
C66: Year 19 | E66: =SUMIF(E287:E298,"<"&99^"99") -> 0 | F66: =SUMIF(F287:F298,"<"&99^"99") -> 0 | G66: =SUMIF(G287:G298,"<"&99^"99") -> 0 | H66: =SUMIF(H287:H298,"<"&99^"99") -> 0 | I66: =SUMIF(I287:I298,"<"&99^"99") -> 0 | K66: =SUMIF(K287:K298,"<"&99^"99") -> 0 | L66: =SUMIF(L287:L298,"<"&99^"99") -> 0 | N66: =SUMIF(N287:N298,"<"&99^"99") -> 0 | P66: =+N66/$E$8 -> 0
C67: Year 20 | E67: =SUMIF(E299:E310,"<"&99^"99") -> 0 | F67: =SUMIF(F299:F310,"<"&99^"99") -> 0 | G67: =SUMIF(G299:G310,"<"&99^"99") -> 0 | H67: =SUMIF(H299:H310,"<"&99^"99") -> 0 | I67: =SUMIF(I299:I310, "<"&99^"99") -> 0 | K67: =SUMIF(K299:K310,"<"&99^"99") -> 0 | L67: =SUMIF(L299:L310, "<"&99^"99") -> 0 | N67: =SUMIF(N299:N310, "<"&99^"99") -> 0 | P67: =+N67/$E$8 -> 0
B69: Monthly Cash Flow
D70: Base Rate PSF | E70: Monthly Base Rent | F70: Rent Tax | G70: PM Fee | H70: CAM, Tax & Ins | I70: Monthly Operating Expenses | K70: Monthly Amortized TI Bucket 1 | L70: Monthly Amortized TI Bucket 2 | N70: Monthly Gross Rent | P70: Annual Gross Rent per SF
B71: =IF(B70+1<=$E$21,B70+1,IF(B70>=$E$21,"",IF(B70="",""))) -> 1 | C71: =E20 -> 46235 | D71: =VLOOKUP(B71,$G$9:$I$29,3) -> 6.06 | E71: =D71*$E$8/12 -> 3888.5 | F71: =IF($C$17="Gross Rent",$B$17*(H71++G71+E71),IF($C$17="Base Rent",$B$17*E71)) -> 0 | G71: =IF($C$16="Base Rent",$B$16*E71,IF($C$16="Gross Rent",$B$16*(H71+E71))) -> 0 | H71: =((SUM(E12:E14)*E8/12))+((SUM(E12:E14)*E8/12))*E15 -> 0 | I71: =SUM(F71:H71) -> 0 | K71: =IF($E$37>B71,0,$E$36 IF(B71>$E$21,0,$E$36)) -> 0 | L71: =IF($F$37>B71,0,$F$36 IF(B71>$E$21,0,$F$36)) -> 0 | N71: =SUM(L71,K71,I71,E71) -> 3888.5 | P71: =+N71/$E$8*12 -> 6.06
B72: =IF(B71+1<=$E$21,B71+1,IF(B71>=$E$21,"",IF(B71="",""))) -> 2 | C72: =IF(B72>$E$21,"", DATE(YEAR(C71),MONTH(C71)+1,DAY(C71))) -> 46266 | D72: =VLOOKUP(B72,$G$9:$I$29,3) -> 6.06 | E72: =D72*$E$8/12 -> 3888.5 | F72: =IF($C$17="Gross Rent",$B$17*(H72+E72),IF($C$17="Base Rent",$B$17*E72)) -> 0 | G72: =IF($C$16="Base Rent",$B$16*E72,IF($C$16="Gross Rent",$B$16*(H72+E72))) -> 0 | H72: =IF(MONTH(C72)=MONTH($E$19),((H71*(1+$E$18))),H71) -> 0 | I72: =SUM(F72:H72) -> 0 | K72: =IF($E$37>B72,0,$E$36 IF(B72>$E$21,0,$E$36)) -> 0 | L72: =IF($F$37>B72,0,$F$36 IF(B72>$E$21,0,$F$36)) -> 0 | N72: =SUM(L72,K72,I72,E72) -> 3888.5 | P72: =+N72/$E$8*12 -> 6.06
B73: =IF(B72+1<=$E$21,B72+1,IF(B72>=$E$21,"",IF(B72="",""))) -> 3 | C73: =IF(B73>$E$21,"", DATE(YEAR(C72),MONTH(C72)+1,DAY(C72))) -> 46296 | D73: =VLOOKUP(B73,$G$9:$I$29,3) -> 6.06 | E73: =D73*$E$8/12 -> 3888.5 | F73: =IF($C$17="Gross Rent",$B$17*(H73+E73),IF($C$17="Base Rent",$B$17*E73)) -> 0 | G73: =IF($C$16="Base Rent",$B$16*E73,IF($C$16="Gross Rent",$B$16*(H73+E73))) -> 0 | H73: =IF(MONTH(C73)=MONTH($E$19),((H72*(1+$E$18))),H72) -> 0 | I73: =SUM(F73:H73) -> 0 | K73: =IF($E$37>B73,0,$E$36 IF(B73>$E$21,0,$E$36)) -> 0 | L73: =IF($F$37>B73,0,$F$36 IF(B73>$E$21,0,$F$36)) -> 0 | N73: =SUM(L73,K73,I73,E73) -> 3888.5 | P73: =+N73/$E$8*12 -> 6.06
B74: =IF(B73+1<=$E$21,B73+1,IF(B73>=$E$21,"",IF(B73="",""))) -> 4 | C74: =IF(B74>$E$21,"", DATE(YEAR(C73),MONTH(C73)+1,DAY(C73))) -> 46327 | D74: =VLOOKUP(B74,$G$9:$I$29,3) -> 6.06 | E74: =D74*$E$8/12 -> 3888.5 | F74: =IF($C$17="Gross Rent",$B$17*(H74+E74),IF($C$17="Base Rent",$B$17*E74)) -> 0 | G74: =IF($C$16="Base Rent",$B$16*E74,IF($C$16="Gross Rent",$B$16*(H74+E74))) -> 0 | H74: =IF(MONTH(C74)=MONTH($E$19),((H73*(1+$E$18))),H73) -> 0 | I74: =SUM(F74:H74) -> 0 | K74: =IF($E$37>B74,0,$E$36 IF(B74>$E$21,0,$E$36)) -> 0 | L74: =IF($F$37>B74,0,$F$36 IF(B74>$E$21,0,$F$36)) -> 0 | N74: =SUM(L74,K74,I74,E74) -> 3888.5 | P74: =+N74/$E$8*12 -> 6.06
B75: =IF(B74+1<=$E$21,B74+1,IF(B74>=$E$21,"",IF(B74="",""))) -> 5 | C75: =IF(B75>$E$21,"", DATE(YEAR(C74),MONTH(C74)+1,DAY(C74))) -> 46357 | D75: =VLOOKUP(B75,$G$9:$I$29,3) -> 6.06 | E75: =D75*$E$8/12 -> 3888.5 | F75: =IF($C$17="Gross Rent",$B$17*(H75+E75),IF($C$17="Base Rent",$B$17*E75)) -> 0 | G75: =IF($C$16="Base Rent",$B$16*E75,IF($C$16="Gross Rent",$B$16*(H75+E75))) -> 0 | H75: =IF(MONTH(C75)=MONTH($E$19),((H74*(1+$E$18))),H74) -> 0 | I75: =SUM(F75:H75) -> 0 | K75: =IF($E$37>B75,0,$E$36 IF(B75>$E$21,0,$E$36)) -> 0 | L75: =IF($F$37>B75,0,$F$36 IF(B75>$E$21,0,$F$36)) -> 0 | N75: =SUM(L75,K75,I75,E75) -> 3888.5 | P75: =+N75/$E$8*12 -> 6.06
B76: =IF(B75+1<=$E$21,B75+1,IF(B75>=$E$21,"",IF(B75="",""))) -> 6 | C76: =IF(B76>$E$21,"", DATE(YEAR(C75),MONTH(C75)+1,DAY(C75))) -> 46388 | D76: =VLOOKUP(B76,$G$9:$I$29,3) -> 6.06 | E76: =D76*$E$8/12 -> 3888.5 | F76: =IF($C$17="Gross Rent",$B$17*(H76+E76),IF($C$17="Base Rent",$B$17*E76)) -> 0 | G76: =IF($C$16="Base Rent",$B$16*E76,IF($C$16="Gross Rent",$B$16*(H76+E76))) -> 0 | H76: =IF(MONTH(C76)=MONTH($E$19),((H75*(1+$E$18))),H75) -> 0 | I76: =SUM(F76:H76) -> 0 | K76: =IF($E$37>B76,0,$E$36 IF(B76>$E$21,0,$E$36)) -> 0 | L76: =IF($F$37>B76,0,$F$36 IF(B76>$E$21,0,$F$36)) -> 0 | N76: =SUM(L76,K76,I76,E76) -> 3888.5 | P76: =+N76/$E$8*12 -> 6.06
B77: =IF(B76+1<=$E$21,B76+1,IF(B76>=$E$21,"",IF(B76="",""))) -> 7 | C77: =IF(B77>$E$21,"", DATE(YEAR(C76),MONTH(C76)+1,DAY(C76))) -> 46419 | D77: =VLOOKUP(B77,$G$9:$I$29,3) -> 6.06 | E77: =D77*$E$8/12 -> 3888.5 | F77: =IF($C$17="Gross Rent",$B$17*(H77+E77),IF($C$17="Base Rent",$B$17*E77)) -> 0 | G77: =IF($C$16="Base Rent",$B$16*E77,IF($C$16="Gross Rent",$B$16*(H77+E77))) -> 0 | H77: =IF(MONTH(C77)=MONTH($E$19),((H76*(1+$E$18))),H76) -> 0 | I77: =SUM(F77:H77) -> 0 | K77: =IF($E$37>B77,0,$E$36 IF(B77>$E$21,0,$E$36)) -> 0 | L77: =IF($F$37>B77,0,$F$36 IF(B77>$E$21,0,$F$36)) -> 0 | N77: =SUM(L77,K77,I77,E77) -> 3888.5 | P77: =+N77/$E$8*12 -> 6.06
B78: =IF(B77+1<=$E$21,B77+1,IF(B77>=$E$21,"",IF(B77="",""))) -> 8 | C78: =IF(B78>$E$21,"", DATE(YEAR(C77),MONTH(C77)+1,DAY(C77))) -> 46447 | D78: =VLOOKUP(B78,$G$9:$I$29,3) -> 6.06 | E78: =D78*$E$8/12 -> 3888.5 | F78: =IF($C$17="Gross Rent",$B$17*(H78+E78),IF($C$17="Base Rent",$B$17*E78)) -> 0 | G78: =IF($C$16="Base Rent",$B$16*E78,IF($C$16="Gross Rent",$B$16*(H78+E78))) -> 0 | H78: =IF(MONTH(C78)=MONTH($E$19),((H77*(1+$E$18))),H77) -> 0 | I78: =SUM(F78:H78) -> 0 | K78: =IF($E$37>B78,0,$E$36 IF(B78>$E$21,0,$E$36)) -> 0 | L78: =IF($F$37>B78,0,$F$36 IF(B78>$E$21,0,$F$36)) -> 0 | N78: =SUM(L78,K78,I78,E78) -> 3888.5 | P78: =+N78/$E$8*12 -> 6.06
B79: =IF(B78+1<=$E$21,B78+1,IF(B78>=$E$21,"",IF(B78="",""))) -> 9 | C79: =IF(B79>$E$21,"", DATE(YEAR(C78),MONTH(C78)+1,DAY(C78))) -> 46478 | D79: =VLOOKUP(B79,$G$9:$I$29,3) -> 6.06 | E79: =D79*$E$8/12 -> 3888.5 | F79: =IF($C$17="Gross Rent",$B$17*(H79+E79),IF($C$17="Base Rent",$B$17*E79)) -> 0 | G79: =IF($C$16="Base Rent",$B$16*E79,IF($C$16="Gross Rent",$B$16*(H79+E79))) -> 0 | H79: =IF(MONTH(C79)=MONTH($E$19),((H78*(1+$E$18))),H78) -> 0 | I79: =SUM(F79:H79) -> 0 | K79: =IF($E$37>B79,0,$E$36 IF(B79>$E$21,0,$E$36)) -> 0 | L79: =IF($F$37>B79,0,$F$36 IF(B79>$E$21,0,$F$36)) -> 0 | N79: =SUM(L79,K79,I79,E79) -> 3888.5 | P79: =+N79/$E$8*12 -> 6.06
B80: =IF(B79+1<=$E$21,B79+1,IF(B79>=$E$21,"",IF(B79="",""))) -> 10 | C80: =IF(B80>$E$21,"", DATE(YEAR(C79),MONTH(C79)+1,DAY(C79))) -> 46508 | D80: =VLOOKUP(B80,$G$9:$I$29,3) -> 6.06 | E80: =D80*$E$8/12 -> 3888.5 | F80: =IF($C$17="Gross Rent",$B$17*(H80+E80),IF($C$17="Base Rent",$B$17*E80)) -> 0 | G80: =IF($C$16="Base Rent",$B$16*E80,IF($C$16="Gross Rent",$B$16*(H80+E80))) -> 0 | H80: =IF(MONTH(C80)=MONTH($E$19),((H79*(1+$E$18))),H79) -> 0 | I80: =SUM(F80:H80) -> 0 | K80: =IF($E$37>B80,0,$E$36 IF(B80>$E$21,0,$E$36)) -> 0 | L80: =IF($F$37>B80,0,$F$36 IF(B80>$E$21,0,$F$36)) -> 0 | N80: =SUM(L80,K80,I80,E80) -> 3888.5 | P80: =+N80/$E$8*12 -> 6.06
B81: =IF(B80+1<=$E$21,B80+1,IF(B80>=$E$21,"",IF(B80="",""))) -> 11 | C81: =IF(B81>$E$21,"", DATE(YEAR(C80),MONTH(C80)+1,DAY(C80))) -> 46539 | D81: =VLOOKUP(B81,$G$9:$I$29,3) -> 6.06 | E81: =D81*$E$8/12 -> 3888.5 | F81: =IF($C$17="Gross Rent",$B$17*(H81+E81),IF($C$17="Base Rent",$B$17*E81)) -> 0 | G81: =IF($C$16="Base Rent",$B$16*E81,IF($C$16="Gross Rent",$B$16*(H81+E81))) -> 0 | H81: =IF(MONTH(C81)=MONTH($E$19),((H80*(1+$E$18))),H80) -> 0 | I81: =SUM(F81:H81) -> 0 | K81: =IF($E$37>B81,0,$E$36 IF(B81>$E$21,0,$E$36)) -> 0 | L81: =IF($F$37>B81,0,$F$36 IF(B81>$E$21,0,$F$36)) -> 0 | N81: =SUM(L81,K81,I81,E81) -> 3888.5 | P81: =+N81/$E$8*12 -> 6.06
B82: =IF(B81+1<=$E$21,B81+1,IF(B81>=$E$21,"",IF(B81="",""))) -> 12 | C82: =IF(B82>$E$21,"", DATE(YEAR(C81),MONTH(C81)+1,DAY(C81))) -> 46569 | D82: =VLOOKUP(B82,$G$9:$I$29,3) -> 6.06 | E82: =D82*$E$8/12 -> 3888.5 | F82: =IF($C$17="Gross Rent",$B$17*(H82+E82),IF($C$17="Base Rent",$B$17*E82)) -> 0 | G82: =IF($C$16="Base Rent",$B$16*E82,IF($C$16="Gross Rent",$B$16*(H82+E82))) -> 0 | H82: =IF(MONTH(C82)=MONTH($E$19),((H81*(1+$E$18))),H81) -> 0 | I82: =SUM(F82:H82) -> 0 | K82: =IF($E$37>B82,0,$E$36 IF(B82>$E$21,0,$E$36)) -> 0 | L82: =IF($F$37>B82,0,$F$36 IF(B82>$E$21,0,$F$36)) -> 0 | N82: =SUM(L82,K82,I82,E82) -> 3888.5 | P82: =+N82/$E$8*12 -> 6.06
B83: =IF(B82+1<=$E$21,B82+1,IF(B82>=$E$21,"",IF(B82="",""))) -> 13 | C83: =IF(B83>$E$21,"", DATE(YEAR(C82),MONTH(C82)+1,DAY(C82))) -> 46600 | D83: =VLOOKUP(B83,$G$9:$I$29,3) -> 6.2418 | E83: =D83*$E$8/12 -> 4005.155 | F83: =IF($C$17="Gross Rent",$B$17*(H83+E83),IF($C$17="Base Rent",$B$17*E83)) -> 0 | G83: =IF($C$16="Base Rent",$B$16*E83,IF($C$16="Gross Rent",$B$16*(H83+E83))) -> 0 | H83: =IF(MONTH(C83)=MONTH($E$19),((H82*(1+$E$18))),H82) -> 0 | I83: =SUM(F83:H83) -> 0 | K83: =IF($E$37>B83,0,$E$36 IF(B83>$E$21,0,$E$36)) -> 0 | L83: =IF($F$37>B83,0,$F$36 IF(B83>$E$21,0,$F$36)) -> 0 | N83: =SUM(L83,K83,I83,E83) -> 4005.155 | P83: =+N83/$E$8*12 -> 6.2418
... B310: =IF(B309+1<=$E$21,B309+1,IF(B309>=$E$21,"",IF(B309="",""))) -> #VALUE! | C310: =IF(B310>$E$21,"", DATE(YEAR(C309),MONTH(C309)+1,DAY(C309))) -> #VALUE! | D310: =VLOOKUP(B310,$G$9:$I$29,3) -> #VALUE! | E310: =D310*$E$8/12 -> #VALUE! | F310: =IF($C$17="Gross Rent",$B$17*(H310+E310),IF($C$17="Base Rent",$B$17*E310)) -> #VALUE! | G310: =IF($C$16="Base Rent",$B$16*E310,IF($C$16="Gross Rent",$B$16*(H310+E310))) -> #VALUE! | H310: =IF(MONTH(C310)=MONTH($E$19),((H309*(1+$E$18))),H309) -> #VALUE! | I310: =SUM(F310:H310) -> #VALUE! | K310: =IF($E$37>B310,0,$E$36 IF(B310>$E$21,0,$E$36)) -> #VALUE! | L310: =IF($F$37>B310,0,$F$36 IF(B310>$E$21,0,$F$36)) -> #VALUE! | N310: =SUM(L310,K310,I310,E310) -> #VALUE! | P310: =+N310/$E$8*12 -> #VALUE!

Sheet Comps
A1: # | B1: Property Name | C1: Address | D1: City | E1: State | F1: Zip Code | G1: Market | H1: Zoning | I1: Latitude | J1: Longitude | K1: Year Built | L1: Building Class | M1: Total Building SF | N1: Building Status | O1: Occupancy Status | P1: Landlord | Q1: Current Tenant | R1: Lease Transaction Type (New Lease/ Sublease/Renewal) | S1: Leased SF | T1: Annual Base Rent (PSF) | U1: Lease Structure | V1: Term (mo) | W1: Free Rent (mo) | X1: Lease Execution | Y1: Lease Commencement Date | Z1: Tenant Improvement (PSF) | AA1: Annual Escalations | AB1: Comments
A2: Subject
A3: 1 | B3: 4310-4340 Cranwood Pky | C3: 4310-4340 Cranwood Pky | D3: Warrensville Heights | E3: OH | F3: 44128 | G3: Cleveland | H3: Industrial | I3: 41.438725 | J3: -81.547049 | K3: 1971 | L3: C | M3: 40950 | N3: Existing | O3: Occupied | P3: Brait Capital, Kumo Capital | R3: New Lease | S3: 7950 | T3: 6 | U3: NNN | X3: 46100 | Y3: 46190 | AB3: Flex space, Suite 4316; starting rent
A4: 2 | B4: 4310-4340 Cranwood Pky | C4: 4310-4340 Cranwood Pky | D4: Warrensville Heights | E4: OH | F4: 44128 | G4: Cleveland | H4: Industrial | I4: 41.438725 | J4: -81.547049 | K4: 1971 | L4: C | M4: 40950 | N4: Existing | O4: Occupied | P4: Brait Capital, Kumo Capital | R4: New Lease | S4: 13560 | T4: 6 | U4: NNN | X4: 46070 | Y4: 46160 | AB4: Flex space, Suite 4310; starting rent
A5: 3 | B5: 12810 Buckeye Rd | C5: 12810 Buckeye Rd | D5: Cleveland | E5: OH | F5: 44120 | G5: Cleveland | H5: Industrial | I5: 41.479846 | J5: -81.592948 | K5: 1921 | L5: C | M5: 7500 | N5: Existing | O5: Occupied | P5: Jared Ray | R5: New Lease | S5: 3645 | T5: 6 | U5: Plus Utilities | X5: 45966 | Y5: 45996 | AB5: Flex space; asking rent
A6: 4 | B6: 23645 Mercantile Rd | C6: 23645 Mercantile Rd | D6: Beachwood | E6: OH | F6: 44122 | G6: Cleveland | H6: Industrial | I6: 41.458706 | J6: -81.508163 | K6: 1975 | L6: B | M6: 67646 | N6: Existing | O6: Occupied | P6: Coven Goldman Associates | R6: New Lease | S6: 16100 | T6: 6 | U6: NNN | X6: 45813 | Y6: 45839 | AB6: Industrial space, Suite D; asking rent
A7: 5 | B7: Prestige Center | C7: 23400 Mercantile Rd | D7: Beachwood | E7: OH | F7: 44122 | G7: Cleveland | H7: Industrial | I7: 41.458542 | J7: -81.510997 | K7: 1968 | L7: B | M7: 34312 | N7: Existing | O7: Occupied | P7: Activity Capital | R7: New Lease | S7: 3324 | T7: 8 | U7: NNN | X7: 45534 | Y7: 45564 | AB7: Flex space, Suite 2; CAM $3.50/SF/Year; asking rent
A8: 6
A9: 7
A10: 8
A11: 9
A12: 10
S15: Median | T15: =MEDIAN(T3:T12) -> 6
S16: Average | T16: =AVERAGE(T3:T12) -> 6.4

Sheet Cost Estimation
B2: Table 1 | O2: Table 2 | P2: *Please do not edit table formulas
B3: Spending Category (If GMP, Enter GMP as the category | C3: Spending Type (Description in GMP Template) | D3: Taxable? (If GMP, Select "No") | E3: Request Team (If GMP, select Construction) | F3: CAPEX/OPEX (Selecting OPEX is very rare) | G3: Previously Approved? | H3: Previous ROM Cost (If using GMP) | I3: GMP/ROM (Enter most up to date cost Estimate) | J3: Delta (If using ROM, leave column empty) | K3: Contingency | L3: Cost Bridge (Please be as detailed as possible) | O3: Summary Table | P3: ROM | Q3: Contingency | R3: Total | S3: Cost Bridge (If total request exceeds 200k)
O4: DD & Design | P4: =SUMIFS(I$4:I$52,$E$4:$E$52,"DD & Design",$G$4:$G$52,"Yes") -> 0 | Q4: =SUMIFS(K$4:K$52,$E$4:$E$52,"DD & Design",$G$4:$G$52,"No") -> 0 | R4: =SUM(P4:Q4) -> 0 | S4: <Enter Bridge here>
O5: Previously Approved Funding* | P5: =SUMIFS($I$4:$I$52,$G$4:$G$52,"Yes") -> 0 | Q5: =SUMIFS($K$4:$K$52,$G$4:$G$52,"Yes") -> 0 | R5: =SUM(P5:Q5) -> 0
O6: ROM Construction | P6: =SUMIFS(I$4:I$52,$E$4:$E$52,"Construction",$G$4:$G$52,"No") -> 0 | Q6: =SUMIFS(K$4:K$52,$E$4:$E$52,"Construction",$G$4:$G$52,"No") -> 0 | R6: =SUM(P6:Q6) -> 0
O7: Startup Costs | P7: =SUMIFS(I$4:I$52,$E$4:$E$52,"Startup",$G$4:$G$52,"No") -> 0 | Q7: =SUMIFS(K$4:K$52,$E$4:$E$52,"Startup",$G$4:$G$52,"No") -> 0 | R7: =SUM(P7:Q7) -> 0
O8: Sales Tax On Construction | P8: =(SUMIFS(I$4:I$52,$E$4:$E$52,"Construction",$G$4:$G$52,"No",$D$4:$D$52,"Yes"))*$P$20 -> 0 | Q8: =(SUMIFS(K$4:K$52,$E$4:$E$52,"Construction",$G$4:$G$52,"No",$D$4:$D$52,"Yes"))*$P$20 -> 0 | R8: =SUM(P8:Q8) -> 0
O9: Sales Tax On Startup | P9: =SUMIFS(I$4:I$52,$E$4:$E$52,"Startup",$G$4:$G$52,"No",$D$4:$D$52,"Yes")*$P$20 -> 0 | Q9: =SUMIFS(K$4:K$52,$E$4:$E$52,"Startup",$G$4:$G$52,"No",$D$4:$D$52,"Yes")*$P$20 -> 0 | R9: =SUM(P9:Q9) -> 0
O10: Current Total Construction Request (excl. Previously approved Funding) | P10: =P6+P8 -> 0 | Q10: =Q6+Q8 -> 0 | R10: =SUM(P10:Q10) -> 0
O11: Total Contruction Cost (Including Previously approved Funding) | P11: =P4+P10 -> 0 | Q11: =Q10+Q5 -> 0 | R11: =SUM(P11:Q11) -> 0
O12: Current Total Startup Request | P12: =P7+P9 -> 0 | Q12: =Q7+Q9 -> 0 | R12: =SUM(P12:Q12) -> 0
O13: Construction & Startup Cost Total | P13: =SUM(P5:P9) -> 0 | Q13: =SUM(Q5:Q9) -> 0 | R13: =SUM(P13:Q13) -> 0
O14: Total OPEX (Construction & Startup) | P14: =SUMIFS(I$4:I$52,$F$4:$F$52,"Opex") -> 0 | Q14: =SUMIFS(K$4:K$52,$F$4:$F$52,"Opex") -> 0 | R14: =SUM(P14:Q14) -> 0
O15: Total CAPEX (Due Diligence, Construction, Startup) | P15: =P13-P14 -> 0 | Q15: =Q13-Q14 -> 0 | R15: =SUM(P15:Q15) -> 0
O16: Tenant Improvement | R16: ='CAR Approval Page 0'!F8 -> 0
O17: Total CAPEX Minus TI (Construction & Startup No Contingency) | P17: =IFERROR(P15-R16,"") -> 0
O18: *Formula assumes previously approved funding is contruction only.
O21: Variables | Q21: Additional Notes
O22: Tax Rate | P22: 0.15 | Q22: Adjust tax rate if required
O26: General ROM Notes: | P26: Template Info
P27: PreCon POC | Q27: <Enter user ID>
P28: Startup POC | Q28: <Enter user ID>
P29: PreCon ROM Date | Q29: <Enter Date>
P30: LOI Draft Date | Q30: <Enter Date>
O31: Enter Additional Notes/Pictures here

Sheet Startup Templates
B2: Orders Per day | C2: Spending Category (If GMP, Enter GMP as the category | D2: Spending Type | E2: Taxable? (If GMP, Select "No") | F2: Request Team | G2: CAPEX/OPEX (Selecting OPEX is very rare) | H2: Previously Approved? | I2: Previous ROM Cost (If using GMP) | J2: GMP/ROM (Enter most up to date cost Estimate) | K2: Delta (If using ROM, leave column empty) | L2: Contingency | M2: Cost Bridge (Please be as detailed as possible)
B3: 1500 Orders Per Day
C4: Previously Approved Funds | D4: Shelving | E4: Yes | F4: Startup | G4: CAPEX | H4: Yes | J4: 31278 | L4: 0
C5: Startup Costs | D5: Startup Costs 3P support | E5: No | F5: Startup | G5: CAPEX | H5: No | J5: 20000 | L5: 0
C6: Startup Costs | D6: Phys Sec | E6: Yes | F6: Startup | G6: CAPEX | H6: No | J6: 5000 | L6: 0
C7: Previously Approved Funds | D7: IT Devices | E7: Yes | F7: Startup | G7: CAPEX | H7: Yes | J7: 11486.09 | L7: 0
C8: Startup Costs | D8: Arc Flash Test | E8: Yes | F8: Startup | G8: CAPEX | H8: No | J8: 8590 | L8: 0
C9: Previously Approved Funds | D9: Module UINs | E9: No | F9: Startup | G9: CAPEX | H9: Yes | J9: 13531.55 | L9: 0
C10: Previously Approved Funds | D10: Cooling Fixture Package | E10: Yes | F10: Startup | G10: CAPEX | H10: Yes | J10: 57300 | L10: 0
C11: Previously Approved Funds | D11: Cooling Fixture Temp Monitoring Package | E11: Yes | F11: Startup | G11: CAPEX | H11: Yes | J11: 3065 | L11: 0
B12: 1250 Orders Per Day | C12: Previously Approved Funds | D12: Shelving | E12: Yes | F12: Startup | G12: CAPEX | H12: No | J12: 26458.41 | L12: 0
C13: Startup Costs | D13: Startup Costs 3P support | E13: No | F13: Startup | G13: CAPEX | H13: No | J13: 20000 | L13: 0
C14: Startup Costs | D14: Phys Sec | E14: Yes | F14: Startup | G14: CAPEX | H14: No | J14: 5000 | L14: 0
C15: Previously Approved Funds | D15: IT Devices | E15: Yes | F15: Startup | G15: CAPEX | H15: Yes | J15: 11486.09 | L15: 0
C16: Startup Costs | D16: Arc Flash Test | E16: Yes | F16: Startup | G16: CAPEX | H16: No | J16: 8590 | L16: 0
C17: Previously Approved Funds | D17: Module UINs | E17: No | F17: Startup | G17: CAPEX | H17: Yes | J17: 13531.55 | L17: 0
C18: Previously Approved Funds | D18: Cooling Fixture Package | E18: Yes | F18: Startup | G18: CAPEX | H18: Yes | J18: 48675 | L18: 0
C19: Previously Approved Funds | D19: Cooling Fixture Temp Monitoring Package | E19: Yes | F19: Startup | G19: CAPEX | H19: Yes | J19: 2655.75 | L19: 0
B20: 1000 Orders Per day | C20: Previously Approved Funds | D20: Cooling Fixture Package | E20: No | F20: Startup | G20: CAPEX | H20: Yes | J20: 42222 | L20: 0 | M20: Per SUEX Cost Matrix 1.12 for 1K order site
C21: Previously Approved Funds | D21: Base Startup BOM costs - Racking | E21: Yes | F21: Startup | G21: CAPEX | H21: Yes | J21: 20722 | L21: 0 | M21: Per SUEX Cost Matrix 1.12 for 1K order site
C22: Startup Costs | D22: Startup Costs 3P support | E22: No | F22: Startup | G22: CAPEX | H22: No | J22: 19880 | L22: 0 | M22: Per SUEX Cost Matrix 1.12 for 1K order site
C23: Startup Costs | D23: Phys Sec | E23: Yes | F23: Startup | G23: CAPEX | H23: No | J23: 5000 | L23: 0 | M23: Per SUEX Cost Matrix 1.12 for 1K order site
C24: Previously Approved Funds | D24: IT Devices | E24: Yes | F24: Startup | G24: CAPEX | H24: Yes | J24: 11486.09 | L24: 0 | M24: Per SUEX Cost Matrix 1.12 for 1K order site
C25: Startup Costs | D25: Arc Flash Test | E25: Yes | F25: Startup | G25: CAPEX | H25: No | J25: 8590 | L25: 0 | M25: Per SUEX Cost Matrix 1.12 for 1K order site
C26: Previously Approved Funds | D26: Module UINs | E26: No | F26: Startup | G26: CAPEX | H26: Yes | J26: 13531.55 | L26: 0 | M26: Per SUEX Cost Matrix 1.12 for 1K order site

Sheet Design

Sheet Site Pictures

Sheet Landlord Work

Sheet Change Log
B3: Update Date | C3: Update Owner | D3: Link To Previous Version | E3: Reason for update

Sheet Scorecard Category_Definitions
B2: Category | C2: Explanations
B3: Financials | C3: The OP breakeven threshold of 250 orders/day translates to 0.05% PDC based on current forecast. Site needs to cover half or 0.025% PDC within 10-min raidus at 12pm to be deemed as close to demand
C5: Asking rent, with room for negotiation.
B6: Site Conditions | C6: 400A or 200A 3 phase is required to support 3.6 DoC, 1k orders/day, based on the current perishable/ambient split
C7: Refrigeration equipment will create significant additional heat in the space. This heat needs to be remediated by the HVAC system.
B8: Operating - Zoning | C8: Zoning codes are bespoke to each jurisdiction, and are often outdated for modern uses. We will need to be nimble in how we present a QC use to a juridiction, and be flexible in how we operate for those which require things like being partially open to the public. This dovetails with some concerns raised for alcohol use below.
B9: Operating - WHS DD | C9: Life safety and health risk to future associates and construction teams. Primary focus on vapor intrusion issues from nearby dry cleaners and gas stations. Corporate liability from pre-existing contamiantion will be covered via lease.
B10: Operating - WHS Safety | C10: See detailed requirements in Appendix D
B11: Operating - Other Tenant Exclusives
